CappedTTLCache/__init__.py
CappedTTLCache/main.py
cappedttlcache-0.1.1.dist-info/LICENSE
cappedttlcache-0.1.1.dist-info/METADATA
cappedttlcache-0.1.1.dist-info/WHEEL
cappedttlcache-0.1.1.dist-info/RECORD
