Metadata-Version: 2.3
Name: cappedttlcache
Version: 0.1.1
Summary: 这是一个用于管理和缓存数据的 Python 模块。该模块支持通用缓存数据存储，具有最大条目数和条目有效时间的限制。
License: MIT
Author: a木木
Author-email: mumuwj0001@163.com
Requires-Python: >=3.10
Classifier: License :: OSI Approved :: MIT License
Classifier: Programming Language :: Python :: 3
Classifier: Programming Language :: Python :: 3.10
Classifier: Programming Language :: Python :: 3.11
Classifier: Programming Language :: Python :: 3.12
Classifier: Programming Language :: Python :: 3.13
